pynim/__init__.py
pynim/build.py
pynim/installer.nsi
pynim-1.0.5.dist-info/METADATA
pynim-1.0.5.dist-info/WHEEL
pynim-1.0.5.dist-info/entry_points.txt
pynim-1.0.5.dist-info/top_level.txt
pynim-1.0.5.dist-info/zip-safe
pynim-1.0.5.dist-info/RECORD
